sensei/__init__.py
sensei/api.py
sensei_cli-0.0.2.data/scripts/sensei
sensei_cli-0.0.2.dist-info/licenses/LICENSE
sensei_cli-0.0.2.dist-info/METADATA
sensei_cli-0.0.2.dist-info/WHEEL
sensei_cli-0.0.2.dist-info/top_level.txt
sensei_cli-0.0.2.dist-info/RECORD
