Metadata-Version: 2.4
Name: sensei-cli
Version: 0.0.2
Summary: Command-line-interface for Sensei Robotics data
Author-email: Sensei Robotics <support@senseirobotics.com>
License-Expression: MIT
Project-URL: Homepage, https://github.com/senseirobotics/sensei-cli
Project-URL: Issues, https://github.com/senseirobotics/sensei-cli/issues
Classifier: Programming Language :: Python :: 3
Classifier: Operating System :: OS Independent
Requires-Python: >=3.9
License-File: LICENSE
Requires-Dist: requests
Requires-Dist: tqdm
Dynamic: license-file
